{
	"name": "Omni",
	"comment": "Generated by Gogh",
	"foreground-color": "#ABB2BF",
	"background-color":"#191622",
	"cursor-background-color": "#ABB2BF",
	"palette": [
		"#191622",
		"#E96379",
		"#67e480",
		"#E89E64",
		"#78D1E1",
		"#988BC7",
		"#FF79C6",
		"#ABB2BF",
		"#000000",
		"#E96379",
		"#67e480",
		"#E89E64",
		"#78D1E1",
		"#988BC7",
		"#FF79C6",
		"#ffffff"
	],
	"use-badge-color": false,
	"use-bold-color": false,
	"use-cursor-color": false,
	"use-highlight-color": false,
	"use-theme-colors": false
}
